behave_xray/__init__.py
behave_xray/authentication.py
behave_xray/evidence.py
behave_xray/exceptions.py
behave_xray/formatter.py
behave_xray/helper.py
behave_xray/hookspecs.py
behave_xray/model.py
behave_xray/xray_publisher.py
behave_xray-0.2.2.dist-info/LICENSE
behave_xray-0.2.2.dist-info/METADATA
behave_xray-0.2.2.dist-info/WHEEL
behave_xray-0.2.2.dist-info/top_level.txt
behave_xray-0.2.2.dist-info/RECORD
