Metadata-Version: 2.1
Name: behave-xray
Version: 0.2.2
Summary: Behave JIRA XRAY results uploader
Home-page: https://github.com/fundakol/behave-xray
Author: Lukasz Fundakowski
Author-email: fundakol@yahoo.com
Keywords: behave JIRA XRAY
Classifier: Development Status :: 4 - Beta
Classifier: Programming Language :: Python :: 3
Classifier: Programming Language :: Python :: 3.7
Classifier: Programming Language :: Python :: 3.8
Classifier: Programming Language :: Python :: 3.9
Classifier: Programming Language :: Python :: 3.10
Classifier: Programming Language :: Python :: 3.11
Classifier: Programming Language :: Python :: 3.12
Classifier: License :: OSI Approved :: Apache Software License
Classifier: Operating System :: OS Independent
License-File: LICENSE
Requires-Dist: behave
Requires-Dist: pluggy
Requires-Dist: requests
